<?xml version="1.0" encoding="iso-8859-1"?>
<!-- Text for Civic help text and pedia -->
<Civ4GameText xmlns="http://www.firaxis.com">
	<TEXT>
		<Tag>TXT_KEY_CIVIC_PREREQ_WAR</Tag>
		<English>[COLOR_RED]Must be at War[COLOR_REVERT]</English>
		<French>[COLOR_RED]Doit &#234;tre en guerre[COLOR_REVERT]</French>
		<German>[COLOR_RED]Muss sich im Krieg befinden[COLOR_REVERT]</German>
		<Spanish>[COLOR_RED]Se debe estar en guerra[COLOR_REVERT]</Spanish>
	</TEXT>
	<TEXT>
		<Tag>TXT_KEY_CIVIC_FOOD_CONSUMPTION_PER_POPULATION</Tag>
		<English>[ICON_BULLET]%d1 food consumed per population (instead of %d2)</English>
		<French>[ICON_BULLET]%d1 nourriture consomm&#233;e par citoyen (au lieu de %d2)</French>
		<German>[ICON_BULLET]%d1 verbrauchte Nahrung pro B&#252;rger (anstatt %d2)</German>
		<Spanish>[ICON_BULLET]%d1 de comida consumida por ciudadano (en lugar de %d2)</Spanish>
	</TEXT>
</Civ4GameText>
